vaede/__init__.py
vaede/__main__.py
vaede/base.py
vaede-0.1.0.dist-info/LICENSE
vaede-0.1.0.dist-info/METADATA
vaede-0.1.0.dist-info/WHEEL
vaede-0.1.0.dist-info/entry_points.txt
vaede-0.1.0.dist-info/top_level.txt
vaede-0.1.0.dist-info/RECORD
