Metadata-Version: 2.1
Name: vaede
Version: 0.1.0
Summary: Awesome vaede created by HeosSacer
Home-page: https://github.com/HeosSacer/VAEDE/
Author: HeosSacer
License: UNKNOWN
Platform: UNKNOWN
License-File: LICENSE
Requires-Dist: typer (~=0.4.0)
Requires-Dist: setuptools (~=58.0.4)
Provides-Extra: test
Requires-Dist: pytest ; extra == 'test'
Requires-Dist: coverage ; extra == 'test'
Requires-Dist: flake8 ; extra == 'test'
Requires-Dist: black ; extra == 'test'
Requires-Dist: isort ; extra == 'test'
Requires-Dist: pytest-cov ; extra == 'test'
Requires-Dist: codecov ; extra == 'test'
Requires-Dist: mypy ; extra == 'test'
Requires-Dist: gitchangelog ; extra == 'test'
Requires-Dist: mkdocs ; extra == 'test'
